Metadata-Version: 2.1
Name: szalik
Version: 1.0.1
Summary: Pakiet testowy
Home-page: http://tekst.pl
License: UNKNOWN
Platform: UNKNOWN
